release_new/__init__.py
release_new/changelog.py
release_new/main.py
release_new/templates/changelog.md
release_new/templates/changelog.rst
release_new-0.17.0.dist-info/METADATA
release_new-0.17.0.dist-info/WHEEL
release_new-0.17.0.dist-info/entry_points.txt
release_new-0.17.0.dist-info/top_level.txt
release_new-0.17.0.dist-info/RECORD
