Metadata-Version: 2.1
Name: release-new
Version: 0.17.0
Summary: logilab's tool to make easy releases on our forge with mercurial
Home-page: https://forge.extranet.logilab.fr/open-source/release-new
Author: Logilab
Author-email: contact@logilab.fr
License: LGPL
Requires-Dist: redbaron<0.10,>=0.9.2
Requires-Dist: jinja2
Requires-Dist: mercurial<7,>=6.5.1
Requires-Dist: tomlkit
Requires-Dist: semver<4.0.0,>=3.0.2
